{
  "schema_version": "wkstruc-ledger/v9",
  "task_id": "v3.3-mainline-a-adaptation",
  "state": "NEEDS_REVIEW",
  "progress": {
    "done": 77,
    "total": 77,
    "label": "77 / 77 steps"
  },
  "last_run": {
    "at": "2026-05-06",
    "agent": "dispatch:patch",
    "summary": "完成 paper2 Mainline-A 新环境适配：新增 benchmark-only export discovery、BenchmarkSchemaAdapter、evidence boundary 展示、diagnostics API、前端 evidence badge/边界警告/结果表格列、compare evidence 混合检测、export evidence 列、删除目标扩展、启动脚本与文档更新。158 passed, 0 failures."
  },
  "validation": {
    "status": "PASS",
    "commands": ["python -m pytest -v"],
    "summary": "158 passed, 116 warnings, 0 failures (22.88s)"
  },
  "open_items": [],
  "checkpoint_id": "checkpoint-v3.3",
  "last_review_report": null,
  "consumed_inbox": []
}
